download_cue/__init__.py
download_cue/cli.py
download_cue/test_cli.py
download_cue-1.0.0.dist-info/licenses/LICENSE
download_cue-1.0.0.dist-info/METADATA
download_cue-1.0.0.dist-info/WHEEL
download_cue-1.0.0.dist-info/entry_points.txt
download_cue-1.0.0.dist-info/top_level.txt
download_cue-1.0.0.dist-info/RECORD
