Metadata-Version: 2.4
Name: download-cue
Version: 1.0.0
Summary: Download cue sheets for audio files
Author-email: Elliot Chance <elliotchance@gmail.com>
License: MIT
Requires-Python: >=3.7
License-File: LICENSE
Requires-Dist: requests
Requires-Dist: beautifulsoup4
Requires-Dist: mutagen
Dynamic: license-file
